bayanpy/BayanImplied.py
bayanpy/__init__.py
bayanpy-0.7.7.dist-info/LICENSE
bayanpy-0.7.7.dist-info/METADATA
bayanpy-0.7.7.dist-info/WHEEL
bayanpy-0.7.7.dist-info/top_level.txt
bayanpy-0.7.7.dist-info/RECORD
