Metadata-Version: 2.1
Name: bayanpy
Version: 0.7.7
Summary: Bayanpy is a powerful Python library for community detection in complex networks, designed to provide optimal or near-optimal solutions for modularity maximization. It features a highly efficient branch-and-cut algorithm and is backed by Integer Programming (IP) formulations.
Home-page: UNKNOWN
Author: UNKNOWN
Author-email: UNKNOWN
License: UNKNOWN
Platform: UNKNOWN
Requires-Dist: requests
Requires-Dist: pandas
Requires-Dist: networkx
Requires-Dist: numpy
Requires-Dist: gurobipy
Requires-Dist: joblib
Requires-Dist: pycombo
